kabu_json_lib/__init__.py
kabu_json_lib/bp.py
kabu_json_lib/datetime_utils.py
kabu_json_lib/logger_config.py
kabu_json_lib/order_formatter.py
kabu_json_lib/symbol_name.py
kabu_json_lib/tradable_codes.py
kabu_json_lib-0.1.12.dist-info/METADATA
kabu_json_lib-0.1.12.dist-info/WHEEL
kabu_json_lib-0.1.12.dist-info/top_level.txt
kabu_json_lib-0.1.12.dist-info/RECORD
