Metadata-Version: 2.4
Name: kabu-json-lib
Version: 0.1.12
Summary: システムトレーディングに必要な計算や便利なPythonライブラリをまとめたパッケージ
Author: umihico
Project-URL: Homepage, https://github.com/umihico/kabu-json-lib
Requires-Python: >=3.8
Requires-Dist: pytz
Requires-Dist: requests
